{
  "gigapan": {
    "roll": null,
    "name": "A train station in New Jersey",
    "is_game": false,
    "snapshottable": true,
    "resolution": 479359000.0,
    "latitude": null,
    "created_at": "2009-07-01T18:31:14-04:00",
    "auth_key": "37c5180ca7e36f3125ba678f5a878342",
    "tiles_requested": 206,
    "taken_at": "2009-06-23T19:27:00-04:00",
    "last_tile_received": null,
    "is_geolocated": false,
    "img_type": "jpg",
    "external_app_id": null,
    "updated_at": "2018-06-30T10:47:18-04:00",
    "is_private": false,
    "stitcher_notes": "GigaPan Stitcher version 0.4.4521 (Macintosh)\nPanorama size: 479 megapixels (36431 x 13158 pixels)\nInput images: 72 (12 columns by 6 rows)\nField of view:  262.3 degrees wide by 94.7 degrees high (top=62.1, bottom=-32.7)\nSettings:\n  All default settings\nOriginal image properties:\n  Camera make: Canon\n  Camera model: Canon PowerShot G9\n  Image size: 4000x3000 (12.0 megapixels)\n  Capture time: 2009-06-23 23:24:33 - 2009-06-23 23:29:20\n  Aperture: f/8\n  Exposure time: 0.025\n  ISO: 80\n  Focal length (35mm equiv.): 69.1 mm\n  Digital zoom: off\n  White balance: Fixed\n  Exposure mode: Manual\nHorizontal overlap: 29.2 to 56.2 percent\nVertical overlap: 31.0 to 31.6 percent\nComputer stats: 4096 MB RAM, 4 CPUs\nTotal time 54:23 (0:45 per picture)\n  Alignment: 1:40, Projection: 4:41, Blending: 48:01\n",
    "field_of_view_w": 262.324,
    "field_of_view_b": -32.669,
    "default_snapshot_id": null,
    "altitude": null,
    "allow_others_to_print": false,
    "views": 883,
    "owner_id": null,
    "id": 27232,
    "user_id": 353,
    "heading": null,
    "explore_score": 1.0,
    "allow_anonymous_snapshotting": false,
    "height": 13158,
    "allow_revenue_sharing": false,
    "longitude": null,
    "levels": 9,
    "description": "The trains to New Jersey are fast and comfortable.  The only problem is that the schedules, especially on the weekend, are a little sparse.\n\nNo real problem if you plan ahead, but a little dicey for casual use - especially if, like Rose, you are used to the Subway which runs more or  less 'all of the time.' \n\nBeing constrained by a train schedule is stressful - not having the option to finish something because the next train is not for an hour is a bit stressful.  OTOH, the trains are clean, and comfortable, and fast, and cheap - $8 for an offpeak round trip.\n",
    "visible": true,
    "tilt": null,
    "embeddable": false,
    "commentable": true,
    "width": 36431,
    "tiles_total": 9953,
    "owner_type": null,
    "options": {
      "snapshot_count": 0,
      "comment_count": 0,
      "bookmark_count": 0
    },
    "field_of_view_h": 94.7452,
    "distance": null,
    "allow_others_to_add_to_gallery": true,
    "tile_base_url": "https://tiles.megazoomquilt.com/panos/27232",
    "tags": [
      "ny_june_2009",
      "nj",
      "new_jersey",
      "train",
      "station"
    ]
  }
}