{
  "gigapan": {
    "roll": 0.0,
    "name": "Burning Man 2009 - Camped in Gerlach (n1_22x8)",
    "is_game": false,
    "snapshottable": true,
    "resolution": 1014410000.0,
    "latitude": 40.649299,
    "created_at": "2010-07-14T18:22:49-04:00",
    "auth_key": "ebd4b6327740a14c309f3bc9328b7b05",
    "tiles_requested": null,
    "taken_at": "2009-09-08T00:00:00-04:00",
    "last_tile_received": null,
    "is_geolocated": true,
    "img_type": "jpg",
    "external_app_id": null,
    "updated_at": "2018-07-20T21:20:54-04:00",
    "is_private": false,
    "stitcher_notes": "GigaPan Stitch version 1.0.0804 (Macintosh)\nPanorama size: 1014 megapixels (60816 x 16680 pixels)\nInput images: 176 (22 columns by 8 rows)\nField of view:  360.0 degrees wide by 98.7 degrees high (top=37.3, bottom=-61.4)\nSettings:\n  All default settings\nOriginal image properties:\n  Camera make: Canon\n  Camera model: Canon PowerShot G9\n  Image size: 4000x3000 (12.0 megapixels)\n  Capture time: 2009-09-08 07:27:17 - 2009-09-08 07:38:16\n  Aperture: f/8\n  Exposure time: 0.0125\n  ISO: 80\n  Focal length (35mm equiv.): 88.4 mm\n  Digital zoom: off\n  White balance: Fixed\n  Exposure mode: Manual\nHorizontal overlap: 28.5 to 67.9 percent\nVertical overlap: 33.4 to 35.3 percent\nComputer stats: 4096 MB RAM, 4 CPUs\nTotal time 51:38 (18 seconds per picture)\n  Alignment: 8:42, Projection: 4:11, Blending: 38:45\n(Preview finished in 31:55)\n",
    "field_of_view_w": 360.0,
    "field_of_view_b": -61.4207,
    "default_snapshot_id": null,
    "altitude": 6.0,
    "allow_others_to_print": false,
    "views": 711,
    "owner_id": null,
    "id": 54446,
    "user_id": 353,
    "heading": 0.0,
    "explore_score": 1.0,
    "allow_anonymous_snapshotting": false,
    "height": 16680,
    "allow_revenue_sharing": false,
    "longitude": -119.359227,
    "levels": 9,
    "description": "We made it out Monday evening and wanted to be in Gerlach during the day so we could check on some things.  So \r\nwe found a corner and made ourselves comfortable.\r\n\r\n\"I assume that is a cow femur\"  Rose\r\nI replied 'we are in Gerlach, never assume anything\"\r\n\"It does look human size to me.  Creepy\"  she replied.",
    "visible": true,
    "tilt": 90.0,
    "embeddable": false,
    "commentable": true,
    "width": 60816,
    "tiles_total": 21035,
    "owner_type": null,
    "options": {
      "snapshot_count": 0,
      "comment_count": 0,
      "bookmark_count": 0
    },
    "field_of_view_h": 98.7372,
    "distance": 15.0,
    "allow_others_to_add_to_gallery": true,
    "tags": [
      "bme",
      "bme2009"
    ],
    "tile_base_url": "https://tiles.megazoomquilt.com/panos/54446"
  }
}