{
  "gigapan": {
    "roll": null,
    "name": "Orrery Model at the Long Now",
    "is_game": false,
    "snapshottable": true,
    "resolution": 286508000.0,
    "latitude": 0.0,
    "created_at": "2011-02-17T18:11:46-05:00",
    "auth_key": "369e3bf325e53179658bbbe629d703b7",
    "tiles_requested": null,
    "taken_at": "2011-02-17T13:09:11-05:00",
    "last_tile_received": null,
    "is_geolocated": false,
    "img_type": "jpg",
    "external_app_id": null,
    "updated_at": "2018-07-13T21:48:18-04:00",
    "is_private": false,
    "stitcher_notes": "GigaPan Stitch version 1.0.0805 (Windows)\nPanorama size: 286 megapixels (14192 x 20188 pixels)\nInput images: 27 (3 columns by 9 rows)\nField of view:  65.5 degrees wide by 93.1 degrees high (top=38.6, bottom=-54.6)\nSettings:\n  All default settings\nOriginal image properties:\n  Camera make: Canon\n  Camera model: Canon EOS REBEL T2i\n  Image size: 5184x3456 (17.9 megapixels)\n  Capture time: 2011-02-17 18:06:44 - 2011-02-17 18:10:11\n  Aperture: f/5.6\n  Exposure time: 0.0333333\n  ISO: 100\n  Focal length (35mm equiv.): 86.5 mm\n  White balance: Fixed\n  Exposure mode: Manual\nHorizontal overlap: 1.8 to 61.9 percent\nVertical overlap: 38.1 to 40.6 percent\nComputer stats: 3892.52 MB RAM, 2 CPUs\nTotal time 9:13 (20 seconds per picture)\n  Alignment: 43 seconds, Projection: 1:53, Blending: 6:36\n(Preview finished in 4:29)\n",
    "field_of_view_w": 65.4814,
    "field_of_view_b": -54.5648,
    "default_snapshot_id": 197575,
    "altitude": null,
    "allow_others_to_print": false,
    "views": 1010,
    "owner_id": null,
    "id": 70907,
    "user_id": 353,
    "heading": null,
    "explore_score": 1.0,
    "allow_anonymous_snapshotting": false,
    "height": 20188,
    "allow_revenue_sharing": false,
    "longitude": 0.0,
    "levels": 8,
    "description": "This is the full Orrery at the Long Now museum.  The last time I shot in the museum I was limited to available light, and so I shot just the base of the Orrery from an angle: http://gigapan.org/gigapans/2770/\n\nNow I have lights (2/17/11), so here I experimented with shooting the full orrery, shooting straight into the window and trusting that I could balance the ambient window light with the light from the flashes.  I had three flashes in this shot, the two main ones on either side, and then a little flash with a purple gell on the base-I am experimenting with the idea of treating curated spaces, like museums, as 'found objects' to be remixed into new compositions solely by the way the spaces are lit.\n\nMy experiments on this have not pregressed very far yet :-)  Right now I am at the point of adding a little new color in one spot, but it seems fun.  And short of a tota colorl remix, having control of light and being able to light all of an interior scene so that it gigapans cleanly is a wonderful goal!  I have so many images of interior spaces which, frankly, are just lacking because of the light.\n",
    "visible": true,
    "tilt": null,
    "embeddable": false,
    "commentable": true,
    "width": 14192,
    "tiles_total": 5923,
    "owner_type": null,
    "options": {
      "snapshot_count": 1,
      "comment_count": 0,
      "bookmark_count": 0
    },
    "field_of_view_h": 93.1467,
    "distance": null,
    "allow_others_to_add_to_gallery": true,
    "tags": [
      "strobist",
      "long_now",
      "orrery"
    ]
  }
}