{"gigapan":{"roll":0.0,"name":"marriot garden (l62)","is_game":false,"snapshottable":true,"resolution":917882000.0,"latitude":21.961677,"created_at":"2008-01-09T10:21:50-05:00","auth_key":"39d1259f3aedf31390bb107e5ce9517c","tiles_requested":142340,"taken_at":"2008-01-04T05:53:00-05:00","last_tile_received":null,"is_geolocated":true,"img_type":"jpg","external_app_id":null,"updated_at":"2018-05-11T07:10:27-04:00","is_private":false,"stitcher_notes":null,"field_of_view_w":178.0,"field_of_view_b":0.0,"default_snapshot_id":8284,"altitude":2.0,"allow_others_to_print":false,"views":8180,"owner_id":null,"id":2477,"user_id":353,"heading":15.0,"explore_score":1.0,"allow_anonymous_snapshotting":false,"height":16095,"allow_revenue_sharing":false,"longitude":-159.350496,"levels":9,"description":"I ran into my Dad and Step Mom.  They were on a tear to go check out the Marriot.  They were told it was beautiful.  And of course it was.  But I don't know how 'beautiful' it really strikes me, as compared with some of the places I photographed.  It is a manicured beauty, a tended beauty.  Somehow artificial.  The beauty of an over decorated haute cuisine meal when compared with fresh fish speared in the afternoon and thrown on the campfire in the evening.  There are no bloody scales in the beauty of the marriot.\r\n\r\n(141mm equivalent)","visible":true,"tilt":90.0,"embeddable":false,"commentable":true,"width":57029,"tiles_total":18829,"owner_type":null,"options":{"snapshot_count":9,"comment_count":0,"bookmark_count":0},"field_of_view_h":50.236,"distance":120.0,"allow_others_to_add_to_gallery":true}}